<instance version="4" description="" template="ebps">
	<list name="extensions">
		<template_reference name="exts" value="ebpextensions\entity_blueprint_ext" List.ItemID="-2078854337" List.ParentItemID="-2078854337">
			<bool name="browsable_in_editor" value="True" overrideParent="True" />
		</template_reference>
		<template_reference name="exts" value="ebpextensions\moving_ext" List.ItemID="2057589443" List.ParentItemID="2057589443">
			<enum_table name="speed_levels">
				<float name="speed_level_0" value="3" overrideParent="True" />
				<float name="speed_level_1" value="4" overrideParent="True" />
				<float name="speed_level_2" value="10" overrideParent="True" />
				<float name="speed_level_3" value="10" overrideParent="True" />
				<float name="speed_level_4" value="10" overrideParent="True" />
			</enum_table>
			<enum_table name="speed_scaling_table">
				<float name="default_speed" value="4.5" overrideParent="True" />
			</enum_table>
		</template_reference>
		<template_reference name="exts" value="ebpextensions\type_ext" List.ItemID="-433665015" List.ParentItemID="-433665015">
			<list name="race_type_list" overrideParent="True">
				<instance_reference name="race_type" value="racebps\french" List.ItemID="1144957450" />
			</list>
		</template_reference>
		<template_reference name="exts" value="ebpextensions\tier_ext" List.ItemID="2081103240" List.ParentItemID="2081103240">
			<list name="tier_group_list">
				<list name="tier_group" List.ItemID="-1937759202" List.ParentItemID="-1937759202">
					<group name="tier" List.ItemID="-1144010367" List.ParentItemID="-1144010367">
						<instance_reference name="attachments" value="attachments\attachment_lists\races\french\units\unit_king_1_fre" overrideParent="True" />
					</group>
				</list>
			</list>
		</template_reference>
	</list>
	<uniqueid name="pbgid" value="183702" />
	<instance_reference name="parent_pbg" value="ebps\races\core\units\unit_king_1" />
</instance>